setup.py
console_colors/__init__.py
console_colors.egg-info/PKG-INFO
console_colors.egg-info/SOURCES.txt
console_colors.egg-info/dependency_links.txt
console_colors.egg-info/top_level.txt