Metadata-Version: 1.0
Name: console-colors
Version: 0.1
Summary: Colors in the terminal
Home-page: http://github.com/jackuess/console_colors
Author: Jacques de Laval
Author-email: chucky@wrutschkow.org
License: MIT
Platform: UNKNOWN
